langchain_runpod/__init__.py
langchain_runpod/chat_models.py
langchain_runpod/llms.py
langchain_runpod/py.typed
langchain_runpod-0.2.0.dist-info/LICENSE
langchain_runpod-0.2.0.dist-info/METADATA
langchain_runpod-0.2.0.dist-info/WHEEL
langchain_runpod-0.2.0.dist-info/RECORD
