Metadata-Version: 2.3
Name: langchain-runpod
Version: 0.2.0
Summary: LangChain integration package for RunPod Serverless AI endpoints.
License: MIT
Keywords: langchain,runpod,llm,ai,serverless
Author: Max Forsey
Author-email: max.forsey@runpod.io
Requires-Python: >=3.9,<4.0
Classifier: Development Status :: 4 - Beta
Classifier: Intended Audience :: Developers
Classifier: License :: OSI Approved :: MIT License
Classifier: Programming Language :: Python :: 3
Classifier: Programming Language :: Python :: 3.9
Classifier: Programming Language :: Python :: 3.10
Classifier: Programming Language :: Python :: 3.11
Classifier: Programming Language :: Python :: 3.12
Classifier: Programming Language :: Python :: 3.13
Classifier: Topic :: Scientific/Engineering :: Artificial Intelligence
Requires-Dist: httpx (>=0.27.0,<0.28.0)
Requires-Dist: langchain-core (>=0.3.15,<0.4.0)
Requires-Dist: pydantic (>=2.10.6,<3.0.0)
Requires-Dist: python-dotenv (>=1.0.1,<2.0.0)
Requires-Dist: requests (>=2.32.3,<3.0.0)
Project-URL: Repository, https://github.com/runpod/langchain-runpod
Project-URL: Release Notes, https://github.com/runpod/langchain-runpod/releases
Project-URL: Source Code, https://github.com/runpod/langchain-runpod
